ecodonut/__init__.py
ecodonut/_version.py
ecodonut/eco_frame/__init__.py
ecodonut/eco_frame/eco_frame.py
ecodonut/eco_frame/eco_layers.py
ecodonut/eco_frame/get_influencers.py
ecodonut/eco_frame/preprocessing.py
ecodonut/eco_frame/territory_mark.py
ecodonut/landscape_vectorizer/__init__.py
ecodonut/landscape_vectorizer/fabdem_bulk_vectorizer.py
ecodonut/landscape_vectorizer/fabdem_vectorizers.py
ecodonut/landscape_vectorizer/glofas_flood_vectorizer.py
ecodonut/landscape_vectorizer/project_fabdem_cache_getter.py
ecodonut/landscape_vectorizer/project_fabdem_vectorizer.py
ecodonut/landscape_vectorizer/soilgrid_vectorizer.py
ecodonut/landscape_vectorizer/tiff_utils.py
ecodonut/river_graph/__init__.py
ecodonut/river_graph/constants.py
ecodonut/river_graph/graph_builder.py
ecodonut/river_graph/spill_sim.py
ecodonut/utils/__init__.py
ecodonut/utils/graph_utils.py
ecodonut/utils/utils.py
ecodonut-3.3.0.dist-info/METADATA
ecodonut-3.3.0.dist-info/WHEEL
ecodonut-3.3.0.dist-info/RECORD
