Metadata-Version: 2.4
Name: ecodonut
Version: 3.3.0
Summary: 
Author: DDonnyy
Author-email: 63115678+DDonnyy@users.noreply.github.com
Requires-Python: >=3.11,<3.13
Classifier: Programming Language :: Python :: 3
Classifier: Programming Language :: Python :: 3.11
Classifier: Programming Language :: Python :: 3.12
Requires-Dist: dask (>=2025.3.0,<2026.0.0)
Requires-Dist: geopandas (>=1.0.1,<2.0.0)
Requires-Dist: loguru (>=0.7.2,<0.8.0)
Requires-Dist: networkx (>=3.3,<4.0)
Requires-Dist: numpy (>=2.1.3,<3.0.0)
Requires-Dist: pandas (>=2.2.3,<3.0.0)
Requires-Dist: pyarrow (>=21.0.0,<22.0.0)
Requires-Dist: scikit-image (>=0.25.2,<0.26.0)
Requires-Dist: scipy (>=1.15.2,<2.0.0)
Requires-Dist: tifffile (>=2025.6.11,<2026.0.0)
Requires-Dist: tqdm (>=4.66.2,<5.0.0)
